[
  { "sira": 1, "parti_kisa_adi": "MİLLET", "parti_adi": "MİLLET PARTİSİ" },
  { "sira": 2, "parti_kisa_adi": "HAK-PAR", "parti_adi": "HAK VE ÖZGÜRLÜKLER PARTİSİ" },
  { "sira": 3, "parti_kisa_adi": "TKP", "parti_adi": "TÜRKİYE KOMÜNİST PARTİSİ" },
  { "sira": 4, "parti_kisa_adi": "TKH", "parti_adi": "TÜRKİYE KOMÜNİST HAREKETİ" },
  { "sira": 5, "parti_kisa_adi": "SOL PARTİ", "parti_adi": "SOL PARTİ" },
  { "sira": 6, "parti_kisa_adi": "GENÇPARTİ", "parti_adi": "GENÇ PARTİ" },
  { "sira": 7, "parti_kisa_adi": "MEMLEKET", "parti_adi": "MEMLEKET PARTİSİ" },
  { "sira": 8, "parti_kisa_adi": "BBP", "parti_adi": "BÜYÜK BİRLİK PARTİSİ" },
  { "sira": 9, "parti_kisa_adi": "AK PARTİ", "parti_adi": "ADALET VE KALKINMA PARTİSİ" },
  { "sira": 10, "parti_kisa_adi": "YENİDEN REFAH", "parti_adi": "YENİDEN REFAH PARTİSİ" },
  { "sira": 11, "parti_kisa_adi": "MHP", "parti_adi": "MİLLİYETÇİ HAREKET PARTİSİ" },
  { "sira": 12, "parti_kisa_adi": "YEŞİL SOL PARTİ", "parti_adi": "YEŞİLLER VE SOL GELECEK PARTİSİ" },
  { "sira": 13, "parti_kisa_adi": "TİP", "parti_adi": "TÜRKİYE İŞÇİ PARTİSİ" },
  { "sira": 14, "parti_kisa_adi": "AB", "parti_adi": "ADALET BİRLİK PARTİSİ" },
  { "sira": 15, "parti_kisa_adi": "ANAP", "parti_adi": "ANAVATAN PARTİSİ" },
  { "sira": 16, "parti_kisa_adi": "YP", "parti_adi": "YENİLİK PARTİSİ" },
  { "sira": 17, "parti_kisa_adi": "HKP", "parti_adi": "HALKIN KURTULUŞ PARTİSİ" },
  { "sira": 18, "parti_kisa_adi": "MİLLİ YOL", "parti_adi": "MİLLİ YOL PARTİSİ" },
  { "sira": 19, "parti_kisa_adi": "VATAN PARTİSİ", "parti_adi": "VATAN PARTİSİ" },
  { "sira": 20, "parti_kisa_adi": "GBP", "parti_adi": "GÜÇ BİRLİĞİ PARTİSİ" },
  { "sira": 21, "parti_kisa_adi": "CHP", "parti_adi": "CUMHURİYET HALK PARTİSİ" },
  { "sira": 22, "parti_kisa_adi": "İYİ PARTİ", "parti_adi": "İYİ PARTİ" },
  { "sira": 23, "parti_kisa_adi": "AP", "parti_adi": "ADALET PARTİSİ" },
  { "sira": 24, "parti_kisa_adi": "ZAFER PARTİSİ", "parti_adi": "ZAFER PARTİSİ" }
]
